dataprotocols/__init__.py
dataprotocols/base/protocol.py
dataprotocols/eryo/__init__.py
dataprotocols/eryo/eryo.py
dataprotocols/eryo/eryo_settings.py
dataprotocols/gsof/__init__.py
dataprotocols/gsof/gsof.py
dataprotocols/gsof/gsof_settings.py
dataprotocols/rt27/rt27.py
dataprotocols/rt27/settings.py
dataprotocols/scripts/eryo.py
dataprotocols/scripts/gsof.py
dataprotocols/scripts/protocol.py
dataprotocols-0.5.16.data/scripts/eryo.py
dataprotocols-0.5.16.data/scripts/gsof.py
dataprotocols-0.5.16.data/scripts/protocol.py
dataprotocols-0.5.16.dist-info/LICENSE
dataprotocols-0.5.16.dist-info/METADATA
dataprotocols-0.5.16.dist-info/WHEEL
dataprotocols-0.5.16.dist-info/entry_points.txt
dataprotocols-0.5.16.dist-info/top_level.txt
dataprotocols-0.5.16.dist-info/RECORD
