Metadata-Version: 2.1
Name: dataprotocols
Version: 0.5.16
Summary: DataProtocols is a set of classes that implement protocols for data acquisition
Home-page: http://gitlab.csn.uchile.cl/dpineda/dataprotocols
Author: David Pineda Osorio
Author-email: dpineda@csn.uchile.cl
License: GPLv3
Platform: UNKNOWN
Requires-Dist: Click
Requires-Dist: networktools
Requires-Dist: basic-logtools
